smartscreen_driver/lcd_comm.py
smartscreen_driver/lcd_comm_rev_a.py
smartscreen_driver/lcd_comm_rev_b.py
smartscreen_driver/lcd_comm_rev_c.py
smartscreen_driver/lcd_comm_rev_d.py
smartscreen_driver/lcd_simulated.py
smartscreen_driver/serialize.py
smartscreen_driver-0.2.3.dist-info/METADATA
smartscreen_driver-0.2.3.dist-info/WHEEL
smartscreen_driver-0.2.3.dist-info/licenses/LICENSE
smartscreen_driver-0.2.3.dist-info/RECORD
