Metadata-Version: 2.4
Name: smartscreen-driver
Version: 0.2.3
Summary: Driver for serial-over-USB displays; library extracted from turing-smart-screen-python
Project-URL: homepage, https://github.com/hchargois/smartscreen-driver
Author-email: Hugo Chargois <hugo.chargois@free.fr>
License-File: LICENSE
Classifier: License :: OSI Approved :: GNU General Public License v3 (GPLv3)
Classifier: Operating System :: OS Independent
Classifier: Programming Language :: Python :: 3
Requires-Python: >=3.9
Requires-Dist: numpy>=2.0.2
Requires-Dist: pillow>=11.1.0
Requires-Dist: pyserial>=3.5
